dgraph_orm/ACL/client.py
dgraph_orm/__init__.py
dgraph_orm/errors.py
dgraph_orm/execute.py
dgraph_orm/generate_orm.py
dgraph_orm/gql_input.py
dgraph_orm/layers.py
dgraph_orm/node.py
dgraph_orm/resolver.py
dgraph_orm/strawberry_helpers/resolvers.py
dgraph_orm/utils/gql.py
dgraph_orm/vendors/edgedb/__init__.py
dgraph_orm/vendors/edgedb/batch.py
dgraph_orm/vendors/edgedb/cache.py
dgraph_orm/vendors/edgedb/constants.py
dgraph_orm/vendors/edgedb/creating_strings.py
dgraph_orm/vendors/edgedb/execute.py
dgraph_orm/vendors/edgedb/gen/aws.py
dgraph_orm/vendors/edgedb/gen/edgedb_DO.py
dgraph_orm/vendors/edgedb/gen/local.py
dgraph_orm/vendors/edgedb/generate.py
dgraph_orm/vendors/edgedb/generator.py
dgraph_orm/vendors/edgedb/graphorm_config.json
dgraph_orm/vendors/edgedb/introspection.py
dgraph_orm/vendors/edgedb/node.py
dgraph_orm/vendors/edgedb/object_types.json
dgraph_orm/vendors/edgedb/query_parsing.py
dgraph_orm/vendors/edgedb/resolver.py
dgraph_orm/vendors/edgedb/span.py
dgraph_orm/vendors/edgedb/unset.py
dgraph_orm-0.2.13.dist-info/WHEEL
dgraph_orm-0.2.13.dist-info/METADATA
dgraph_orm-0.2.13.dist-info/RECORD
